radvel/__init__.py
radvel/basis.py
radvel/cli.py
radvel/driver.py
radvel/fitting.py
radvel/gp.py
radvel/kepler.py
radvel/likelihood.py
radvel/mcmc.py
radvel/model.py
radvel/nested_sampling.py
radvel/orbit.py
radvel/posterior.py
radvel/prior.py
radvel/report.py
radvel/utils.py
radvel/plot/__init__.py
radvel/plot/mcmc_plots.py
radvel/plot/orbit_plots.py
radvel/templates/fig_corner.tex
radvel/templates/fig_corner_derived_pars.tex
radvel/templates/fig_rv_multipanel.tex
radvel/templates/report.tex
radvel/templates/tab_comparison.tex
radvel/templates/tab_crit.tex
radvel/templates/tab_derived.tex
radvel/templates/tab_params.tex
radvel/templates/tab_prior_summary.tex
radvel/templates/tab_rv.tex
radvel/tests/test_api.py
radvel/tests/test_cli.py
radvel/tests/test_nb.py
radvel-1.5.0.dist-info/METADATA
radvel-1.5.0.dist-info/WHEEL
radvel-1.5.0.dist-info/entry_points.txt
radvel-1.5.0.dist-info/licenses/LICENSE
radvel-1.5.0.dist-info/RECORD
