Metadata-Version: 2.4
Name: radvel
Version: 1.5.0
Summary: General Toolkit for Modeling Radial Velocities
Project-URL: Homepage, https://github.com/California-Planet-Search/radvel
Project-URL: Documentation, http://radvel.readthedocs.io/
Project-URL: Repository, https://github.com/California-Planet-Search/radvel
Author: BJ Fulton, Erik Petigura, Sarah Blunt, Evan Sinukoff
License: The MIT License (MIT)
License-File: LICENSE
Classifier: Development Status :: 4 - Beta
Classifier: Intended Audience :: Science/Research
Classifier: License :: OSI Approved :: MIT License
Classifier: Programming Language :: Python :: 3
Classifier: Programming Language :: Python :: 3.8
Classifier: Programming Language :: Python :: 3.9
Classifier: Programming Language :: Python :: 3.11
Classifier: Programming Language :: Python :: 3.12
Classifier: Topic :: Scientific/Engineering :: Astronomy
Classifier: Topic :: Scientific/Engineering :: Physics
Requires-Python: >=3.8
Requires-Dist: astropy>=1.1.2
Requires-Dist: corner>=2.0
Requires-Dist: cython>=0.23
Requires-Dist: dill
Requires-Dist: emcee>=3.0.2
Requires-Dist: h5py>=3.9.0
Requires-Dist: ipykernel>=4.10.0
Requires-Dist: ipython
Requires-Dist: jinja2>=2.9
Requires-Dist: jupyter-client>=5.2.4
Requires-Dist: matplotlib>=1.5.3
Requires-Dist: nbsphinx==0.9.3
Requires-Dist: numpy
Requires-Dist: pandas>=0.20.0
Requires-Dist: python-dateutil>=2.5.0
Requires-Dist: scipy
Requires-Dist: tables
Requires-Dist: ultranest
